clemcore/__init__.py
clemcore/clemeval.py
clemcore/cli.py
clemcore/backends/__init__.py
clemcore/backends/anthropic_api.py
clemcore/backends/backend_registry.py
clemcore/backends/cohere_api.py
clemcore/backends/google_api.py
clemcore/backends/huggingface_local_api.py
clemcore/backends/huggingface_multimodal_api.py
clemcore/backends/initial_hf_check.py
clemcore/backends/key_registry.py
clemcore/backends/llamacpp_api.py
clemcore/backends/mistral_api.py
clemcore/backends/model_registry.json
clemcore/backends/model_registry.py
clemcore/backends/model_registry_eos_check.py
clemcore/backends/multimodal_utils.py
clemcore/backends/openai_api.py
clemcore/backends/openai_compatible_api.py
clemcore/backends/openrouter_api.py
clemcore/backends/slurk_api.py
clemcore/backends/utils.py
clemcore/backends/vllm_api.py
clemcore/clemgame/__init__.py
clemcore/clemgame/benchmark.py
clemcore/clemgame/errors.py
clemcore/clemgame/events.py
clemcore/clemgame/instances.py
clemcore/clemgame/master.py
clemcore/clemgame/metrics.py
clemcore/clemgame/player.py
clemcore/clemgame/recorder.py
clemcore/clemgame/registry.py
clemcore/clemgame/resources.py
clemcore/clemgame/callbacks/__init__.py
clemcore/clemgame/callbacks/base.py
clemcore/clemgame/callbacks/files.py
clemcore/clemgame/envs/__init__.py
clemcore/clemgame/envs/environment.py
clemcore/clemgame/envs/master.py
clemcore/clemgame/envs/grid_environment/__init__.py
clemcore/clemgame/envs/grid_environment/grid_environment.py
clemcore/clemgame/envs/grid_environment/inclusive_grid_environment.py
clemcore/clemgame/envs/openenv/__init__.py
clemcore/clemgame/envs/openenv/client.py
clemcore/clemgame/envs/openenv/models.py
clemcore/clemgame/envs/openenv/server/__init__.py
clemcore/clemgame/envs/openenv/server/app.py
clemcore/clemgame/envs/openenv/server/environment.py
clemcore/clemgame/envs/pettingzoo/__init__.py
clemcore/clemgame/envs/pettingzoo/master.py
clemcore/clemgame/envs/pettingzoo/wrappers.py
clemcore/clemgame/legacy/__init__.py
clemcore-3.4.0.dist-info/licenses/LICENSE
clemcore-3.4.0.dist-info/METADATA
clemcore-3.4.0.dist-info/WHEEL
clemcore-3.4.0.dist-info/entry_points.txt
clemcore-3.4.0.dist-info/top_level.txt
clemcore-3.4.0.dist-info/RECORD
