Metadata-Version: 2.4
Name: clemcore
Version: 3.4.0
Summary: The cLLM (chat-optimized Large Language Model, 'clem') framework tests such models' ability to engage in games, that is, rule-constituted activities played using language.
Author-email: Philipp Sadler <first.last@uni-potsdam.de>, Jonathan Jordan <first.last@uni-potsdam.de>, Sherzod Hakimov <first.last@uni-potsdam.de>, Anne Beyer <first.last@uni-potsdam.de>, "L. Pfennigschmidt" <first.last@uni-potsdam.de>, Kushal Koshti <first.last@uni-potsdam.de>
License: MIT
Project-URL: Homepage, https://github.com/clp-research/clemcore
Requires-Python: <3.13,>=3.10
License-File: LICENSE
Requires-Dist: pyyaml>=6.0
Requires-Dist: numpy<2.0.0,>=1.24.3
Requires-Dist: retry>=0.9.2
Requires-Dist: tqdm>=4.65.0
Requires-Dist: nltk==3.8.1
Requires-Dist: openai<3.0.0,>=2.15.0
Requires-Dist: anthropic<1.0.0,>=0.75.0
Requires-Dist: cohere<6.0.0,>=5.20.1
Requires-Dist: google-genai<2.0.0,>=1.57.0
Requires-Dist: mistralai~=1.10.0
Requires-Dist: matplotlib==3.7.1
Requires-Dist: pandas==2.0.1
Requires-Dist: seaborn==0.12.2
Requires-Dist: sparklines~=0.7.0
Requires-Dist: pylatex~=1.4.2
Requires-Dist: ordered-set~=4.1.0
Requires-Dist: markdown~=3.8.2
Requires-Dist: pettingzoo~=1.25.0
Requires-Dist: openenv-core~=0.1.1
Requires-Dist: datasets~=4.4.1
Provides-Extra: vllm
Requires-Dist: torch~=2.6.0; extra == "vllm"
Requires-Dist: transformers==4.55.2; extra == "vllm"
Requires-Dist: vllm==0.8.4; extra == "vllm"
Provides-Extra: huggingface
Requires-Dist: torch~=2.1.1; extra == "huggingface"
Requires-Dist: torchvision==0.16.1; extra == "huggingface"
Requires-Dist: accelerate==1.2.1; extra == "huggingface"
Requires-Dist: bitsandbytes==0.45.5; extra == "huggingface"
Requires-Dist: peft==0.17.0; extra == "huggingface"
Requires-Dist: timm<=1.0.19,>=1.0.15; extra == "huggingface"
Requires-Dist: transformers==4.55.2; extra == "huggingface"
Provides-Extra: slurk
Requires-Dist: python-engineio==4.4.0; extra == "slurk"
Requires-Dist: python-socketio==5.7.2; extra == "slurk"
Requires-Dist: websocket-client; extra == "slurk"
Dynamic: license-file
